odoo8_addon_l10n_ch_hr_payroll-8.0.1.2.0.99.dev26-py2.7-nspkg.pth
odoo8_addon_l10n_ch_hr_payroll-8.0.1.2.0.99.dev26.dist-info/DESCRIPTION.rst
odoo8_addon_l10n_ch_hr_payroll-8.0.1.2.0.99.dev26.dist-info/METADATA
odoo8_addon_l10n_ch_hr_payroll-8.0.1.2.0.99.dev26.dist-info/RECORD
odoo8_addon_l10n_ch_hr_payroll-8.0.1.2.0.99.dev26.dist-info/WHEEL
odoo8_addon_l10n_ch_hr_payroll-8.0.1.2.0.99.dev26.dist-info/metadata.json
odoo8_addon_l10n_ch_hr_payroll-8.0.1.2.0.99.dev26.dist-info/namespace_packages.txt
odoo8_addon_l10n_ch_hr_payroll-8.0.1.2.0.99.dev26.dist-info/top_level.txt
odoo_addons/l10n_ch_hr_payroll/README.rst
odoo_addons/l10n_ch_hr_payroll/__init__.py
odoo_addons/l10n_ch_hr_payroll/__openerp__.py
odoo_addons/l10n_ch_hr_payroll/data/hr.salary.rule.category.xml
odoo_addons/l10n_ch_hr_payroll/data/hr.salary.rule.xml
odoo_addons/l10n_ch_hr_payroll/i18n/ar.po
odoo_addons/l10n_ch_hr_payroll/i18n/bg.po
odoo_addons/l10n_ch_hr_payroll/i18n/bs.po
odoo_addons/l10n_ch_hr_payroll/i18n/ca.po
odoo_addons/l10n_ch_hr_payroll/i18n/cs.po
odoo_addons/l10n_ch_hr_payroll/i18n/de.po
odoo_addons/l10n_ch_hr_payroll/i18n/el_GR.po
odoo_addons/l10n_ch_hr_payroll/i18n/en_GB.po
odoo_addons/l10n_ch_hr_payroll/i18n/es.po
odoo_addons/l10n_ch_hr_payroll/i18n/es_CR.po
odoo_addons/l10n_ch_hr_payroll/i18n/es_EC.po
odoo_addons/l10n_ch_hr_payroll/i18n/es_MX.po
odoo_addons/l10n_ch_hr_payroll/i18n/es_PE.po
odoo_addons/l10n_ch_hr_payroll/i18n/et.po
odoo_addons/l10n_ch_hr_payroll/i18n/fi.po
odoo_addons/l10n_ch_hr_payroll/i18n/fr.po
odoo_addons/l10n_ch_hr_payroll/i18n/fr_CA.po
odoo_addons/l10n_ch_hr_payroll/i18n/fr_CH.po
odoo_addons/l10n_ch_hr_payroll/i18n/gl.po
odoo_addons/l10n_ch_hr_payroll/i18n/hr.po
odoo_addons/l10n_ch_hr_payroll/i18n/hr_HR.po
odoo_addons/l10n_ch_hr_payroll/i18n/hu.po
odoo_addons/l10n_ch_hr_payroll/i18n/id.po
odoo_addons/l10n_ch_hr_payroll/i18n/it.po
odoo_addons/l10n_ch_hr_payroll/i18n/ja.po
odoo_addons/l10n_ch_hr_payroll/i18n/lt.po
odoo_addons/l10n_ch_hr_payroll/i18n/mk.po
odoo_addons/l10n_ch_hr_payroll/i18n/mn.po
odoo_addons/l10n_ch_hr_payroll/i18n/nb.po
odoo_addons/l10n_ch_hr_payroll/i18n/nb_NO.po
odoo_addons/l10n_ch_hr_payroll/i18n/nl.po
odoo_addons/l10n_ch_hr_payroll/i18n/nl_BE.po
odoo_addons/l10n_ch_hr_payroll/i18n/nl_NL.po
odoo_addons/l10n_ch_hr_payroll/i18n/pl.po
odoo_addons/l10n_ch_hr_payroll/i18n/pt.po
odoo_addons/l10n_ch_hr_payroll/i18n/pt_BR.po
odoo_addons/l10n_ch_hr_payroll/i18n/pt_PT.po
odoo_addons/l10n_ch_hr_payroll/i18n/ro.po
