Metadata-Version: 2.0
Name: odoo8-addon-l10n-ch-hr-payroll
Version: 8.0.1.2.0.99.dev26
Summary: Swizerland Payroll Rules
Home-page: http://open-net.ch
Author: Open Net Sàrl,Odoo Community Association (OCA)
Author-email: support@odoo-community.org
License: AGPL-3
Platform: UNKNOWN
Classifier: Programming Language :: Python
Classifier: Framework :: Odoo
Classifier: License :: OSI Approved :: GNU Affero General Public License v3
Requires-Python: ~=2.7
Requires-Dist: odoo (<9.0a,>=8.0a)
